BRSAScore/BRSAScore.py
BRSAScore/__init__.py
BRSAScore/pickle/BRScores_uspto_emolecules.pkl.gz
BRSAScore/pickle/BScores_emolecules.pkl.gz
BRSAScore/pickle/RScores_uspto.pkl.gz
BRSAScore-0.1.0.dist-info/LICENSE
BRSAScore-0.1.0.dist-info/METADATA
BRSAScore-0.1.0.dist-info/WHEEL
BRSAScore-0.1.0.dist-info/top_level.txt
BRSAScore-0.1.0.dist-info/RECORD
