Metadata-Version: 2.1
Name: BRSAScore
Version: 0.1.0
Summary: Reaction and Resource-aware SAScore
Author: Shuan Chen
License: MIT
Requires-Python: >=3.6
License-File: LICENSE
Requires-Dist: numpy (>=1.16.4)
Requires-Dist: matplotlib (>=3.3.4)
Requires-Dist: rdkit-pypi (>=2021)
